LycorisR.py
LycorisR-1.5.3.dist-info/LICENSE
LycorisR-1.5.3.dist-info/METADATA
LycorisR-1.5.3.dist-info/WHEEL
LycorisR-1.5.3.dist-info/top_level.txt
LycorisR-1.5.3.dist-info/RECORD
