Metadata-Version: 2.1
Name: LycorisR
Version: 1.5.3
Summary: A lightweight recommendation algorithm framework based on LycorisNet.
Home-page: https://github.com/RootHarold/LycorisR
Author: RootHarold
Author-email: rootharold@163.com
License: UNKNOWN
Platform: UNKNOWN
Requires-Dist: LycorisNet (>=2.5)
Requires-Dist: numpy (>=1.18)
